newiotclient/__init__.py
newiotclient/__main__.py
newiotclient/core.py
newiotclient/cert/ca-bundle.crt
newiotclient-1.0.2.dist-info/LICENCE
newiotclient-1.0.2.dist-info/METADATA
newiotclient-1.0.2.dist-info/WHEEL
newiotclient-1.0.2.dist-info/top_level.txt
newiotclient-1.0.2.dist-info/zip-safe
newiotclient-1.0.2.dist-info/RECORD
