Metadata-Version: 2.1
Name: newiotclient
Version: 1.0.2
Summary: python client for iot.lonelyassistant.com
Home-page: https://github.com/laonan/newiot-pyclient
Author: Laonan
Author-email: hello@laonan.net
License: UNKNOWN
Project-URL: Bug Tracker, https://github.com/laonan/newiot-pyclient/issues
Platform: UNKNOWN
Classifier: Programming Language :: Python :: 3
Classifier: License :: OSI Approved :: MIT License
Classifier: Operating System :: OS Independent
Requires-Python: >=3.6
License-File: LICENCE
Requires-Dist: requests (>=2.27.1)
Requires-Dist: paho-mqtt (>=1.6.1)
